llsubtitles/__main__.py
llsubtitles/ankideck.py
llsubtitles/dictionaries/chinese.py
llsubtitles/dictionaries/data/chinese-english.json
llsubtitles/templates/pinyin-english.json
llsubtitles/transcribe.py
llsubtitles-1.0.1.dist-info/METADATA
llsubtitles-1.0.1.dist-info/WHEEL
llsubtitles-1.0.1.dist-info/LICENSE
llsubtitles-1.0.1.dist-info/entry_points.txt
llsubtitles-1.0.1.dist-info/RECORD
