Metadata-Version: 2.1
Name: llsubtitles
Version: 1.0.1
Summary: Use OpenAI's whisper to generate subtitles in multiple languages for the purpose of language learning
License: MIT
Author: Brian Moody
Author-email: brian.k.moody@outlook.com
Requires-Python: >=3.8,<4.0
Classifier: License :: OSI Approved :: MIT License
Classifier: Programming Language :: Python :: 3
Classifier: Programming Language :: Python :: 3.8
Classifier: Programming Language :: Python :: 3.9
Classifier: Programming Language :: Python :: 3.10
Classifier: Programming Language :: Python :: 3.11
Requires-Dist: openai-whisper (>=20230124,<20230125)
Requires-Dist: xpinyin (>=0.7.6,<0.8.0)
